mimicbot/__init__.py
mimicbot/bot.py
mimicbot/cli.py
mimicbot/twitter.py
mimicbot/data/config.ini
mimicbot/filter/__init__.py
mimicbot/generate/__init__.py
mimicbot/generate/markov.py
mimicbot/process/__init__.py
mimicbot-0.0.16.dist-info/DESCRIPTION.rst
mimicbot-0.0.16.dist-info/METADATA
mimicbot-0.0.16.dist-info/RECORD
mimicbot-0.0.16.dist-info/WHEEL
mimicbot-0.0.16.dist-info/entry_points.txt
mimicbot-0.0.16.dist-info/metadata.json
mimicbot-0.0.16.dist-info/top_level.txt
