Metadata-Version: 2.0
Name: mimicbot
Version: 0.0.16
Summary: A Twitter mimic bot
Home-page: https://github.com/nslater/mimicbot
Author: Naomi Slater
Author-email: nslater@tumbolia.org
License: Apache License 2.0
Keywords: twitter bot
Platform: UNKNOWN
Classifier: Development Status :: 1 - Planning
Classifier: Environment :: Console
Classifier: Intended Audience :: End Users/Desktop
Classifier: License :: OSI Approved :: Apache Software License
Classifier: Natural Language :: English
Classifier: Operating System :: OS Independent
Classifier: Programming Language :: Python
Classifier: Programming Language :: Python :: 3
Classifier: Topic :: Artistic Software
Requires-Dist: setuptools
Requires-Dist: markovify
Requires-Dist: twitter
Requires-Dist: pyparsing
Requires-Dist: click
Requires-Dist: Whoosh
Requires-Dist: python-dateutil
Requires-Dist: asteval
